{"errors":[],"warnings":[],"namedChunkGroups":{"polyfill":{"chunks":[3,11],"assets":["webpack-runtime-1d9209d8d1108e0acfc9.js","webpack-runtime-1d9209d8d1108e0acfc9.js.map","polyfill-30a761bdd526fe06de9d.js","polyfill-30a761bdd526fe06de9d.js.map"],"children":{},"childAssets":{}},"app":{"chunks":[3,10,5],"assets":["webpack-runtime-1d9209d8d1108e0acfc9.js","webpack-runtime-1d9209d8d1108e0acfc9.js.map","framework-6c3ead24af170cdcb87c.js","framework-6c3ead24af170cdcb87c.js.map","app-8c09bc09947cada73425.js","app-8c09bc09947cada73425.js.map"],"children":{},"childAssets":{}},"component---src-pages-about-js":{"chunks":[2,0,1,6],"assets":["styles.e4709efbb44970f70533.css","styles-7d4153d260c0197f0043.js","styles-7d4153d260c0197f0043.js.map","1bfc9850-4ab7906dc0b2fe8bbfa0.js","1bfc9850-4ab7906dc0b2fe8bbfa0.js.map","commons-6a3dc2c309a4ddf2e507.js","commons-6a3dc2c309a4ddf2e507.js.map","component---src-pages-about-js-9bc3873de3f104239061.js","component---src-pages-about-js-9bc3873de3f104239061.js.map"],"children":{},"childAssets":{}},"component---src-pages-consortium-js":{"chunks":[2,0,1,7],"assets":["styles.e4709efbb44970f70533.css","styles-7d4153d260c0197f0043.js","styles-7d4153d260c0197f0043.js.map","1bfc9850-4ab7906dc0b2fe8bbfa0.js","1bfc9850-4ab7906dc0b2fe8bbfa0.js.map","commons-6a3dc2c309a4ddf2e507.js","commons-6a3dc2c309a4ddf2e507.js.map","component---src-pages-consortium-js-e8402f3693cd70a4d9dc.js","component---src-pages-consortium-js-e8402f3693cd70a4d9dc.js.map"],"children":{},"childAssets":{}},"component---src-pages-index-js":{"chunks":[2,0,1,8],"assets":["styles.e4709efbb44970f70533.css","styles-7d4153d260c0197f0043.js","styles-7d4153d260c0197f0043.js.map","1bfc9850-4ab7906dc0b2fe8bbfa0.js","1bfc9850-4ab7906dc0b2fe8bbfa0.js.map","commons-6a3dc2c309a4ddf2e507.js","commons-6a3dc2c309a4ddf2e507.js.map","component---src-pages-index-js-86224a101ea788ba0ba4.js","component---src-pages-index-js-86224a101ea788ba0ba4.js.map"],"children":{},"childAssets":{}},"component---src-pages-methodology-js":{"chunks":[2,0,1,9],"assets":["styles.e4709efbb44970f70533.css","styles-7d4153d260c0197f0043.js","styles-7d4153d260c0197f0043.js.map","1bfc9850-4ab7906dc0b2fe8bbfa0.js","1bfc9850-4ab7906dc0b2fe8bbfa0.js.map","commons-6a3dc2c309a4ddf2e507.js","commons-6a3dc2c309a4ddf2e507.js.map","component---src-pages-methodology-js-d2f5aaf8914c41b8eb1c.js","component---src-pages-methodology-js-d2f5aaf8914c41b8eb1c.js.map"],"children":{},"childAssets":{}}},"assetsByChunkName":{"polyfill":["webpack-runtime-1d9209d8d1108e0acfc9.js","polyfill-30a761bdd526fe06de9d.js"],"app":["webpack-runtime-1d9209d8d1108e0acfc9.js","framework-6c3ead24af170cdcb87c.js","app-8c09bc09947cada73425.js"],"component---src-pages-about-js":["styles.e4709efbb44970f70533.css","styles-7d4153d260c0197f0043.js","1bfc9850-4ab7906dc0b2fe8bbfa0.js","commons-6a3dc2c309a4ddf2e507.js","component---src-pages-about-js-9bc3873de3f104239061.js"],"component---src-pages-consortium-js":["styles.e4709efbb44970f70533.css","styles-7d4153d260c0197f0043.js","1bfc9850-4ab7906dc0b2fe8bbfa0.js","commons-6a3dc2c309a4ddf2e507.js","component---src-pages-consortium-js-e8402f3693cd70a4d9dc.js"],"component---src-pages-index-js":["styles.e4709efbb44970f70533.css","styles-7d4153d260c0197f0043.js","1bfc9850-4ab7906dc0b2fe8bbfa0.js","commons-6a3dc2c309a4ddf2e507.js","component---src-pages-index-js-86224a101ea788ba0ba4.js"],"component---src-pages-methodology-js":["styles.e4709efbb44970f70533.css","styles-7d4153d260c0197f0043.js","1bfc9850-4ab7906dc0b2fe8bbfa0.js","commons-6a3dc2c309a4ddf2e507.js","component---src-pages-methodology-js-d2f5aaf8914c41b8eb1c.js"]}}